proteusAI/__init__.py
proteusAI/Library/__init__.py
proteusAI/Library/library.py
proteusAI/Library/__pycache__/__init__.cpython-38.pyc
proteusAI/Library/__pycache__/library.cpython-38.pyc
proteusAI/Model/__init__.py
proteusAI/Model/model.py
proteusAI/Model/__pycache__/__init__.cpython-38.pyc
proteusAI/Model/__pycache__/model.cpython-38.pyc
proteusAI/Protein/__init__.py
proteusAI/Protein/protein.py
proteusAI/Protein/__pycache__/__init__.cpython-38.pyc
proteusAI/Protein/__pycache__/protein.cpython-38.pyc
proteusAI/__pycache__/__init__.cpython-38.pyc
proteusAI/data_tools/MSA.py
proteusAI/data_tools/__init__.py
proteusAI/data_tools/pdb.py
proteusAI/design_tools/Constraints.py
proteusAI/design_tools/MCMC.py
proteusAI/design_tools/ZeroShot.py
proteusAI/design_tools/__init__.py
proteusAI/io_tools/__init__.py
proteusAI/io_tools/embeddings.py
proteusAI/io_tools/fasta.py
proteusAI/io_tools/__pycache__/__init__.cpython-38.pyc
proteusAI/io_tools/__pycache__/embeddings.cpython-38.pyc
proteusAI/io_tools/__pycache__/fasta.cpython-38.pyc
proteusAI/io_tools/matrices/BLOSUM50
proteusAI/io_tools/matrices/BLOSUM62
proteusAI/io_tools/matrices/alphabet
proteusAI/mining_tools/__init__.py
proteusAI/mining_tools/alphafoldDB.py
proteusAI/mining_tools/blast.py
proteusAI/mining_tools/uniprot.py
proteusAI/ml_tools/__init__.py
proteusAI/ml_tools/__pycache__/__init__.cpython-38.pyc
proteusAI/ml_tools/bo_tools/__init__.py
proteusAI/ml_tools/bo_tools/acq_fn.py
proteusAI/ml_tools/bo_tools/genetic_algorithm.py
proteusAI/ml_tools/bo_tools/__pycache__/__init__.cpython-38.pyc
proteusAI/ml_tools/bo_tools/__pycache__/acq_fn.cpython-38.pyc
proteusAI/ml_tools/bo_tools/__pycache__/genetic_algorithm.cpython-38.pyc
proteusAI/ml_tools/esm_tools/__init__.py
proteusAI/ml_tools/esm_tools/alphabet.pt
proteusAI/ml_tools/esm_tools/esm_tools.py
proteusAI/ml_tools/esm_tools/__pycache__/__init__.cpython-38.pyc
proteusAI/ml_tools/esm_tools/__pycache__/esm_tools.cpython-38.pyc
proteusAI/ml_tools/sklearn_tools/__init__.py
proteusAI-0.0.2.dist-info/LICENSE
proteusAI-0.0.2.dist-info/METADATA
proteusAI-0.0.2.dist-info/WHEEL
proteusAI-0.0.2.dist-info/top_level.txt
proteusAI-0.0.2.dist-info/RECORD
