Metadata-Version: 2.1
Name: proteusAI
Version: 0.0.2
Summary: ProteusAI is a python package designed for AI driven protein engineering.
Home-page: https://github.com/jonfunk21/ProteusAI
Author: Jonathan Funk
Author-email: funk.jonathan21@gmail.com
Requires-Python: >=3.8
License-File: LICENSE
Requires-Dist: torch ==2.4
Requires-Dist: torch-geometric
Requires-Dist: torch-scatter
Requires-Dist: uvicorn
Requires-Dist: asgiref
Requires-Dist: starlette
Requires-Dist: shiny
Requires-Dist: pandas
Requires-Dist: numpy
Requires-Dist: requests
Requires-Dist: scipy
Requires-Dist: fair-esm
Requires-Dist: matplotlib
Requires-Dist: biopython
Requires-Dist: biotite
Requires-Dist: scikit-learn
Requires-Dist: optuna
Requires-Dist: seaborn
Requires-Dist: openpyxl
Requires-Dist: py3Dmol
Requires-Dist: gpytorch
Requires-Dist: openmm
Requires-Dist: umap-learn
Requires-Dist: proteusAI
Provides-Extra: dev
Requires-Dist: black ; extra == 'dev'
Requires-Dist: ruff ; extra == 'dev'
Requires-Dist: pytest ; extra == 'dev'
Provides-Extra: docs
Requires-Dist: sphinx ; extra == 'docs'
Requires-Dist: sphinx-book-theme ; extra == 'docs'
Requires-Dist: myst-nb ; extra == 'docs'
Requires-Dist: ipywidgets ; extra == 'docs'
Requires-Dist: sphinx-new-tab-link !=0.2.2 ; extra == 'docs'
Requires-Dist: jupytext ; extra == 'docs'
